krkn_lib_kubernetes_draft/__init__.py
krkn_lib_kubernetes_draft/client.py
krkn_lib_kubernetes_draft/client_tests.py
krkn_lib_kubernetes_draft/resources.py
krkn_lib_kubernetes_draft-0.1.11.dist-info/LICENSE
krkn_lib_kubernetes_draft-0.1.11.dist-info/METADATA
krkn_lib_kubernetes_draft-0.1.11.dist-info/WHEEL
krkn_lib_kubernetes_draft-0.1.11.dist-info/RECORD
