Metadata-Version: 2.1
Name: krkn-lib-kubernetes-draft
Version: 0.1.11
Summary: Kubernetes library for Kraken
Home-page: https://github.com/redhat-chaos/krkn
License: Apache-2.0
Author: Red Hat Chaos Engineering Team
Requires-Python: >=3.9,<4.0
Classifier: License :: OSI Approved :: Apache Software License
Classifier: Programming Language :: Python :: 3
Classifier: Programming Language :: Python :: 3.9
Classifier: Programming Language :: Python :: 3.10
Classifier: Programming Language :: Python :: 3.11
Requires-Dist: arcaflow-lib-kubernetes (>=0.1.1,<0.2.0)
Requires-Dist: kubernetes (>=26.0.0,<27.0.0)
Requires-Dist: sphinxnotes-markdown-builder (>=0.5.6,<0.6.0)
